spada/__init__.py
spada/utils.py
spada/bio/__init__.py
spada/bio/aminoacid.py
spada/bio/gene_expression.py
spada/bio/polypeptide.py
spada/bio/protein.py
spada/bio/switch.py
spada/bio/transcript.py
spada/biological_entities/__init__.py
spada/biological_entities/aminoacid.py
spada/biological_entities/gene_expression.py
spada/biological_entities/protein.py
spada/biological_entities/switch.py
spada/biological_entities/transcript.py
spada/data/gencode_genes.pkl
spada/data/gencode_transcripts.pkl
spada/interface/__init__.py
spada/interface/out_network.py
spada/io/__init__.py
spada/io/error.py
spada/io/io.py
spada/meta/__init__.py
spada/methods/__init__.py
spada/methods/compute_switches.py
spada/methods/create_network.py
spada/methods/get_switches.py
spada/methods/method.py
spada/methods/result_summary.py
spada/methods/simulate_switches.py
spada/methods/structural_analysis.py
spada/methods/summary.py
spada/methods/test.py
spada/methods/wes_mutations_feature_overlap.py
spada/network/__init__.py
spada/network/ensembl_gene_network.py
spada/network/ensembl_transcript_network.py
spada/network/gencode_gene_network.py
spada/network/gencode_isoform_network.py
spada/network/gencode_transcript_network.py
spada/network/gene_network.py
spada/network/isoform_network.py
spada/network/network.py
spada/network/transcript_network.py
spada/network/ucsc_gene_network.py
spada/network/ucsc_isoform_network.py
spada/network/ucsc_transcript_network.py
spada-1.26.5.data/scripts/spada
spada-1.26.5.dist-info/LICENSE.txt
spada-1.26.5.dist-info/METADATA
spada-1.26.5.dist-info/WHEEL
spada-1.26.5.dist-info/top_level.txt
spada-1.26.5.dist-info/RECORD
