Metadata-Version: 2.1
Name: spada
Version: 1.26.5
Summary: Find splicing-led, functional changes of the proteome.
Home-page: https://github.com/hclimente/spada
Author: Héctor Climente-González
Author-email: hector.climente@curie.fr
License: MIT
Download-URL: https://github.com/hclimente/spada/archive/v1.9.1.tar.gz
Keywords: alternative,splicing,analysis,transcriptomics,networks
Platform: UNKNOWN
Classifier: Development Status :: 4 - Beta
Classifier: Topic :: Scientific/Engineering :: Bio-Informatics
Classifier: Intended Audience :: Science/Research
Classifier: Intended Audience :: Healthcare Industry
Classifier: License :: OSI Approved :: MIT License
Classifier: Operating System :: OS Independent
Classifier: Programming Language :: Python :: 3 :: Only
Requires-Dist: networkx (>=1.11)
Requires-Dist: numpy (>=1.13.1)
